mumbletemps/__init__.py
mumbletemps/admin.py
mumbletemps/app_settings.py
mumbletemps/apps.py
mumbletemps/auth_hooks.py
mumbletemps/models.py
mumbletemps/tasks.py
mumbletemps/urls.py
mumbletemps/views.py
mumbletemps/locale/django.pot
mumbletemps/locale/cs/LC_MESSAGES/django.po
mumbletemps/locale/de/LC_MESSAGES/django.po
mumbletemps/locale/es/LC_MESSAGES/django.po
mumbletemps/locale/fr_FR/LC_MESSAGES/django.po
mumbletemps/locale/it_IT/LC_MESSAGES/django.po
mumbletemps/locale/ja/LC_MESSAGES/django.po
mumbletemps/locale/ko_KR/LC_MESSAGES/django.po
mumbletemps/locale/nl/LC_MESSAGES/django.po
mumbletemps/locale/pl_PL/LC_MESSAGES/django.po
mumbletemps/locale/ru/LC_MESSAGES/django.po
mumbletemps/locale/sk/LC_MESSAGES/django.po
mumbletemps/locale/uk/LC_MESSAGES/django.po
mumbletemps/locale/zh_Hans/LC_MESSAGES/django.po
mumbletemps/migrations/0001_initial.py
mumbletemps/migrations/0002_tempuser.py
mumbletemps/migrations/0003_auto_20200604_1020.py
mumbletemps/migrations/0004_auto_20200605_0828.py
mumbletemps/migrations/0005_tempuser_templink.py
mumbletemps/migrations/0006_tempuser_character_id.py
mumbletemps/migrations/__init__.py
mumbletemps/static/mumbletemps/images/mumble-icon.png
mumbletemps/templates/mumbletemps/base.html
mumbletemps/templates/mumbletemps/index.html
mumbletemps/templates/mumbletemps/link.html
mumbletemps/templates/mumbletemps/login.html
mumbletemps/templatetags/__init__.py
mumbletemps/templatetags/timetags.py
allianceauth_mumbletemps-3.0.2.dist-info/METADATA
allianceauth_mumbletemps-3.0.2.dist-info/WHEEL
allianceauth_mumbletemps-3.0.2.dist-info/licenses/LICENSE
allianceauth_mumbletemps-3.0.2.dist-info/RECORD
