Metadata-Version: 2.3
Name: allianceauth-mumbletemps
Version: 3.0.2
Summary: Mumble Temp Links plugin for Alliance Auth
Project-URL: Changelog, https://github.com/Solar-Helix-Independent-Transport/allianceauth-mumble-temp/blob/master/CHANGELOG.md
Project-URL: Documentation, https://github.com/Solar-Helix-Independent-Transport/allianceauth-mumble-temp/blob/master/README.md
Project-URL: Homepage, https://github.com/Solar-Helix-Independent-Transport/allianceauth-mumble-temp
Project-URL: Source, https://github.com/Solar-Helix-Independent-Transport/allianceauth-mumble-temp.git
Project-URL: Tracker, https://github.com/Solar-Helix-Independent-Transport/allianceauth-mumble-temp/issues
Author-email: Aaron Kable <aaronkable@gmail.com>
License: MIT License
License-File: LICENSE
Keywords: allianceauth,eveonline,mumble
Classifier: Environment :: Web Environment
Classifier: Framework :: Django
Classifier: Framework :: Django :: 4.2
Classifier: Intended Audience :: Developers
Classifier: License :: OSI Approved :: GNU General Public License v3 (GPLv3)
Classifier: Operating System :: OS Independent
Classifier: Programming Language :: Python
Classifier: Programming Language :: Python :: 3 :: Only
Classifier: Programming Language :: Python :: 3.8
Classifier: Programming Language :: Python :: 3.9
Classifier: Programming Language :: Python :: 3.10
Classifier: Programming Language :: Python :: 3.11
Classifier: Programming Language :: Python :: 3.12
Classifier: Topic :: Internet :: WWW/HTTP
Classifier: Topic :: Internet :: WWW/HTTP :: Dynamic Content
Requires-Python: >=3.8
Requires-Dist: allianceauth<5.0.0,>=4
